yolov4/__init__.py
yolov4/darknet.py
yolov4/helpers.py
yolo_v4-0.5.dist-info/METADATA
yolo_v4-0.5.dist-info/WHEEL
yolo_v4-0.5.dist-info/top_level.txt
yolo_v4-0.5.dist-info/RECORD
